ovos_skill_audio_recording/LICENSE
ovos_skill_audio_recording/MANIFEST.in
ovos_skill_audio_recording/README.md
ovos_skill_audio_recording/__init__.py
ovos_skill_audio_recording/requirements.txt
ovos_skill_audio_recording/version.py
ovos_skill_audio_recording/locale/ca-es/skill.json
ovos_skill_audio_recording/locale/ca-es/intents/start_recording.intent
ovos_skill_audio_recording/locale/da-dk/skill.json
ovos_skill_audio_recording/locale/da-dk/intents/start_recording.intent
ovos_skill_audio_recording/locale/de-de/skill.json
ovos_skill_audio_recording/locale/de-de/intents/start_recording.intent
ovos_skill_audio_recording/locale/en-us/skill.json
ovos_skill_audio_recording/locale/en-us/intents/start_recording.intent
ovos_skill_audio_recording/locale/es-es/intents/start_recording.intent
ovos_skill_audio_recording/locale/eu/intents/start_recording.intent
ovos_skill_audio_recording/locale/fr-fr/intents/start_recording.intent
ovos_skill_audio_recording/locale/gl-es/intents/start_recording.intent
ovos_skill_audio_recording/locale/it-it/intents/start_recording.intent
ovos_skill_audio_recording/locale/pt-pt/intents/start_recording.intent
ovos_skill_audio_recording/ovos_skill_audio_recording.egg-info/PKG-INFO
ovos_skill_audio_recording/ovos_skill_audio_recording.egg-info/SOURCES.txt
ovos_skill_audio_recording/ovos_skill_audio_recording.egg-info/dependency_links.txt
ovos_skill_audio_recording/ovos_skill_audio_recording.egg-info/entry_points.txt
ovos_skill_audio_recording/ovos_skill_audio_recording.egg-info/top_level.txt
ovos_skill_audio_recording-0.2.7.dist-info/LICENSE
ovos_skill_audio_recording-0.2.7.dist-info/METADATA
ovos_skill_audio_recording-0.2.7.dist-info/WHEEL
ovos_skill_audio_recording-0.2.7.dist-info/entry_points.txt
ovos_skill_audio_recording-0.2.7.dist-info/top_level.txt
ovos_skill_audio_recording-0.2.7.dist-info/RECORD
