Metadata-Version: 2.1
Name: ovos-skill-audio-recording
Version: 0.2.7
Summary: OVOS audio recording skill
Home-page: https://github.com/OpenVoiceOS/ovos-skill-audio-recording
Author: OpenVoiceOS
Author-email: jarbasai@mailfence.com
License: Apache-2.0
Keywords: ovos skill plugin
License-File: LICENSE
